{
  "uuid": "795db186c71b306614d449b7455b54a9",
  "sourceCode": "Employer Portal",
  "title": "Assistant Manager, IT (2 year contract) - hybrid arrangement",
  "description": "<p>You will be responsible for the end‑to‑end planning, execution,governance, and successful delivery of IT and digital transformationinitiatives. Your role ensures that project objectives, operationalrequirements, and governance standards are consistently achieved, while fostering alignment across internal departments, external vendors, senior leadership, and key stakeholders. Success in this position requires the ability to bridge business and technology by collaborating effectively with technical teams, translating business needs into actionable solutions, and guiding implementation without requiring deep developer expertise.</p><p><br /><strong>Job Responsibilities</strong></p><p><br /><strong>Project Planning & Governance</strong></p><ul><li>Lead <strong>end‑to‑end project lifecycle</strong> in accordance with Project Management Guidelines.</li></ul><ul><li>Prepare and maintain all mandatory artefacts: Project Charter, Business Case, RFP & Vendor Score Sheets, Project Plan & Timeline, Risk & Control registers, Testing documentation, Project Closure File.</li></ul><ul><li>Ensure <strong>mandatory approval gates</strong> are met with clear documentation for risk, procurement, and senior management reviews.</li></ul><p><br /><strong>Stakeholder & Cross‑Functional Coordination</strong></p><ul><li>Engage extensively with benefiting departments (operations, product owners, clinical teams, finance, HR, procurement).</li><li>Collect business requirements, validate process flows, and ensure operational alignment.</li><li>Manage complex stakeholder networks including senior management and external vendors.</li></ul><p><br /><strong>Vendor & Project Team Management</strong></p><ul><li>Review vendor proposals, scope, timelines, and resourcing.</li><li>Coordinate solution design, development, configuration, testing, and deployment.</li><li>Oversee vendor performance and contract adherence.</li><li>Provide project leadership to IT team members and cross‑functional project contributors.</li></ul><p><br /><strong>Execution & Delivery</strong></p><ul><li>Coordinate system design discussions, UAT planning, test scenario reviews, defect resolution and retesting.</li><li>Manage go‑live activities, technical cutover, post‑go‑live review and handover to operations.</li><li>Track project risks, issues, dependencies, and mitigation strategies.</li></ul><p><br /><strong>Reporting & Compliance</strong></p><ul><li>Ensure auditability and traceability for all project artefacts.</li><li>Provide updates on progress, budget, risks, and mitigation.</li><li>Ensure compliance with governance, procurement, and finance requirements.</li><li>Timely KPI reporting to Grant providers.</li></ul><p><br /><strong>Requirements</strong></p><ul><li>Bachelor Degree in IT, Computer Science, Engineering, or relevant field.</li><li>Min 6 yrs of experience, with at least 3 years in a managerial capacity.</li><li>Strong planning, documentation, and project governance capabilities.</li><li>Exp in managing vendors and system implementation projects (preferred: case management systems, CRM,  finance and HR systems).</li><li>Strong communication and stakeholder engagement skills.</li><li>Able to work under pressure and manage multiple parallel workstreams.</li><li>Exp in Government Grant application and KPI reporting.</li><li>Exp in Social Service Agencies will be an advantage.</li><li>Exp in Project management methodologies (Waterfall, Agile hybrid).</li><li>Strong understanding of full stack web development concepts (front-end, back-end, databases, APIs) sufficient to collaborate with technical teams and translate requirements, without needing to code at a developer level.</li><li>Working knowledge of Salesforce CRM capabilities, workflows, and integration points, with the ability to gather requirements and liaise with developers/administrators rather than perform hands-on configuration.</li><li>Familiarity with process automation using low‑code/no‑code platforms (e.g., Power Automate, n8n, Salesforce Flow), with the ability to design and optimize workflows in collaboration with technical teams.</li><li>Strong analytical, problem‑solving, communication skills and decision‑making skills. </li><li>Ability to lead cross‑functional teams.</li></ul>",
  "minimumYearsExperience": 6,
  "shiftPattern": null,
  "schemes": [],
  "skills": [
    {
      "skill": "Charter",
      "uuid": "11347b3d404f701a75282a7993e0dda4",
      "confidence": null,
      "isKeySkill": false
    },
    {
      "skill": "System Implementation",
      "uuid": "139474c545a1fc8f2a120e839165a0ee",
      "confidence": null,
      "isKeySkill": false
    },
    {
      "skill": "UAT",
      "uuid": "19dd6c1cec504ac854645f352eb03209",
      "confidence": null,
      "isKeySkill": false
    },
    {
      "skill": "Process Automation",
      "uuid": "27746d2889a20e07549a4ed41eb9f5fd",
      "confidence": null,
      "isKeySkill": false
    },
    {
      "skill": "Translating",
      "uuid": "5a46a951446636631a92cf8a7b8a21ea",
      "confidence": null,
      "isKeySkill": false
    },
    {
      "skill": "Agile",
      "uuid": "657fd3eec6624217c3ad5de3744a69d2",
      "confidence": null,
      "isKeySkill": false
    },
    {
      "skill": "Traceability",
      "uuid": "759f4372df506ee3ab42a77b95d7980c",
      "confidence": null,
      "isKeySkill": false
    },
    {
      "skill": "Stakeholder Engagement",
      "uuid": "867e5c27fed3f9f4f75a8996b1ff2d19",
      "confidence": null,
      "isKeySkill": false
    },
    {
      "skill": "System Design",
      "uuid": "98bf5c1a28c1981bf8d74d4bc73ceaab",
      "confidence": null,
      "isKeySkill": false
    },
    {
      "skill": "Compliance",
      "uuid": "9c0408c775a2b61052a2e700a89f396f",
      "confidence": null,
      "isKeySkill": false
    },
    {
      "skill": "Project Management",
      "uuid": "9c1330f0dda3f188a3813b9840d1143f",
      "confidence": null,
      "isKeySkill": false
    },
    {
      "skill": "Case Management",
      "uuid": "d799928eb48a88cb861f3283005d227a",
      "confidence": null,
      "isKeySkill": false
    },
    {
      "skill": "Bridge",
      "uuid": "de8504b73ea228d0ea9bbce69752092e",
      "confidence": null,
      "isKeySkill": false
    },
    {
      "skill": "Web Development",
      "uuid": "e9f65fa4000d038efa0cdff8bb824632",
      "confidence": null,
      "isKeySkill": false
    },
    {
      "skill": "Business Requirements",
      "uuid": "fb7ef3df0fd8ed7b3630bad089942103",
      "confidence": null,
      "isKeySkill": false
    }
  ],
  "flexibleWorkArrangements": [
    {
      "id": 2,
      "flexibleWorkArrangement": "Telecommuting"
    }
  ],
  "otherRequirements": null,
  "ssocCode": "12199",
  "occupationId": "OCC001483",
  "ssocVersion": "2020v2",
  "workingHours": null,
  "numberOfVacancies": 1,
  "psdUrl": null,
  "categories": [
    {
      "id": 21,
      "category": "Information Technology"
    }
  ],
  "employmentTypes": [
    {
      "id": 3,
      "employmentType": "Contract"
    }
  ],
  "positionLevels": [
    {
      "id": 3,
      "position": "Manager"
    }
  ],
  "status": {
    "id": 102,
    "jobStatus": "Open"
  },
  "ssecEqa": "70",
  "ssecFos": "0919",
  "postedCompany": {
    "uen": "202111519K",
    "description": "<p>(1) Our Origins</p>\n<p><br></p>\n<p>Dementia Singapore (DSG) was formed in 1990 as Alzheimer’s Disease Association to better serve Singapore’s growing dementia community, increase awareness about dementia, and reduce the stigma surrounding the condition.</p>\n<p><br></p>\n<p>As Singapore’s leading Social Service Agency (SSA) in specialised dementia care, Dementia Singapore aims to advocate for the needs of people living with dementia and their families; empower the community through capability-building, knowledge and consultancy; and deliver quality, person-centred care innovations.</p>\n<p><br></p>\n<p>For more information, visit https://dementia.org.sg/</p>\n<p><br></p>\n<p><br></p>\n<p>(2) Our Employee Value Proposition</p>\n<p><br></p>\n<p>Because We Care</p>\n<p><br></p>\n<p>“We are professionals committed to enhancing dementia care in Singapore.</p>\n<p><br></p>\n<p>We support each other in our common pursuit to inspire society to regard and respect persons living with dementia as individuals to lead purposeful and meaningful lives and create a more compassionate society.</p>\n<p><br></p>\n<p>Communication, openness and innovation are key traits within our family. We listen to each other’s feedback and suggestions, and work together collaboratively to make DSG a better place to work in.</p>\n<p><br></p>\n<p>We care for the well-being of our team so that we can provide the highest standard of care to our clients. This includes providing for career growth for all employees of DSG, while catering for good work-life harmony to allow for personal growth and development.”</p>\n<p><br></p>\n<p><br></p>\n<p>(3) Hybrid Work Arrangement</p>\n<p><br></p>\n<p>As part of our Work-Life Harmony strategy, we adopted a hybrid work arrangement (subject to the nature of the job).</p>\n<p><br>\nFlexi-Time</p>\n<p><br>\nWe have Staggered Timing for staff to choose their starting and ending work hours.<br>\n</p>\n<p>At DSG, we believe that achieving work-life balance will allow every valued staff of the DSG family to satisfy their professional and personal goals.</p>\n<p><br></p>\n<p><br></p>\n<p>(4) Diversity, Equity &amp; Inclusion at the Heart of Our Culture<br>\n<br>\nAt Dementia Singapore, diversity, equity, and inclusion are not add-ons, they are integral to who we are and how we work. We embrace a culture where every team member feels valued, respected, and empowered to contribute meaningfully.&nbsp;</p>\n<p><br>\nWe are committed to providing equal opportunities for career development, and we believe that diverse perspectives lead to better outcomes for the people we serve.<br>\n</p>\n<p><br></p>",
    "name": "DEMENTIA SINGAPORE LTD.",
    "ssicCode": "88992",
    "employeeCount": 180,
    "companyUrl": "https://dementia.org.sg",
    "lastSyncDate": "2026-02-03T06:25:36.000Z",
    "ssicCode2020": "88992",
    "_links": {
      "self": {
        "href": "https://api.mycareersfuture.gov.sg/v2/companies/202111519K"
      },
      "jobs": {
        "href": "https://api.mycareersfuture.gov.sg/v2/companies/202111519K/jobs"
      },
      "addresses": {
        "href": "https://api.mycareersfuture.gov.sg/v2/companies/202111519K/addresses"
      },
      "schemes": {
        "href": "https://api.mycareersfuture.gov.sg/v2/companies/202111519K/schemes"
      }
    },
    "logoFileName": "7dcb9d22374e3d490483705d65fc6cb3/dementia-singapore.png",
    "logoUploadPath": "https://static.mycareersfuture.gov.sg/images/company/logos/7dcb9d22374e3d490483705d65fc6cb3/dementia-singapore.png",
    "responsiveEmployer": {
      "isResponsive": true
    }
  },
  "hiringCompany": null,
  "address": {
    "overseasCountry": null,
    "foreignAddress1": null,
    "foreignAddress2": null,
    "block": "20",
    "street": "BENDEMEER ROAD",
    "floor": null,
    "unit": null,
    "building": "BS BENDEMEER CENTRE",
    "postalCode": "339914",
    "isOverseas": false,
    "districts": [
      {
        "id": 12,
        "location": "D12 Balestier, Serangoon, Toa Payoh",
        "region": "Central",
        "sectors": [
          "31",
          "32",
          "33"
        ],
        "regionId": "Central"
      }
    ],
    "lat": 1.31438877469966,
    "lng": 103.862146047281
  },
  "metadata": {
    "jobPostId": "MCF-2026-0167717",
    "deletedAt": null,
    "createdBy": "ec879eaf-35e9-40d4-9972-88bebf298b53",
    "createdAt": "2026-01-27T08:55:10.000Z",
    "updatedAt": "2026-01-27T08:55:10.000Z",
    "emailRecipient": "ec879eaf-35e9-40d4-9972-88bebf298b53",
    "editCount": 0,
    "repostCount": 0,
    "totalNumberOfView": 115,
    "newPostingDate": "2026-01-27",
    "originalPostingDate": "2026-01-27",
    "expiryDate": "2026-02-26",
    "totalNumberJobApplication": 13,
    "isPostedOnBehalf": false,
    "isHideSalary": false,
    "isHideCompanyAddress": false,
    "isHideHiringEmployerName": false,
    "isHideEmployerName": false,
    "jobDetailsUrl": "https://www.mycareersfuture.gov.sg/job/information-technology/assistant-manager-hybrid-arrangement-dementia-singapore-795db186c71b306614d449b7455b54a9",
    "matchedSkillsScore": null
  },
  "salary": {
    "maximum": 1,
    "minimum": 1,
    "type": {
      "id": 4,
      "salaryType": "Monthly"
    }
  },
  "_links": {
    "self": {
      "href": "https://api.mycareersfuture.gov.sg/v2/jobs/795db186c71b306614d449b7455b54a9"
    },
    "screeningQuestions": {
      "href": "https://api.mycareersfuture.gov.sg/v2/jobs/795db186c71b306614d449b7455b54a9/screening-questions"
    }
  },
  "jobTitles": []
}