{
  "uuid": "587007e6a06683489166f7e7b2af4ff4",
  "sourceCode": "Employer Portal",
  "title": "Assistant Section Head (Deli - Cold & Hot Kitchen)",
  "description": "<p><u><strong>Job Responsibilties</strong></u></p>\n<ul>\n  <li>Develop and maintain production schedules for the Deli - Cold/Hot Kitchen team to meet daily and weekly sales demands.</li>\n  <li>Oversee the preparation of all cold deli items, ensuring adherence to recipes, portion control, and presentation standards.</li>\n  <li>Implement and maintain safe food handling practices, including temperature control, sanitation, and HACCP guidelines.</li>\n  <li>Monitor inventory levels and requisition supplies to maintain smooth operations.</li>\n  <li>Minimize waste through proper yield management and production planning.</li>\n  <li>Lead, motivate, and coach a team of Deli - Cold/Hot Kitchen staff, providing training and development opportunities.</li>\n  <li>Conduct performance reviews and hold team members accountable for meeting production goals and quality standards.</li>\n  <li>Foster a positive and collaborative work environment, promoting teamwork and communication.</li>\n  <li>Conduct regular quality checks on all cold deli items, ensuring freshness, taste, and presentation.</li>\n  <li>Develop and implement systems to maintain consistent product quality.</li>\n  <li>Investigate and resolve any product quality issues.</li>\n  <li>Maintain accurate production records and documentation.</li>\n  <li>Assist with the development of new cold deli recipes and menu items.</li>\n  <li>Identify and implement cost-saving measures within the Cold Kitchen operation.</li>\n  <li>Participate in inventory management and ordering processes.</li>\n  <li>Ensure a clean, organized, and safe work environment in the Cold Kitchen.</li>\n</ul>\n<p><u><strong>Jobs Requirements</strong></u></p>\n<ul>\n  <li>Min. Diploma in Culinary or its related field.</li>\n  <li>Minimum 5 years of experience in a similar industry such as a high-volume food production environment (deli, central kitchen preferred).</li>\n  <li>Strong understanding of cold food preparation, including food safety regulations (HACCP preferred).</li>\n  <li>Excellent organizational and time management skills.</li>\n  <li>The ability to lead and motivate a team in a fast-paced environment.</li>\n  <li>Excellent communication and interpersonal skills.</li>\n  <li>Proficient in inventory management.</li>\n  <li>Ability to work independently and as part of a team.</li>\n  <li>Strong work ethic and a commitment to quality and efficiency.</li>\n  <li>Able to work well under pressure in a fast-paced environment</li>\n  <li>Able to work on weekends, public holidays and shift work.</li>\n</ul>",
  "minimumYearsExperience": 5,
  "shiftPattern": null,
  "schemes": [],
  "skills": [
    {
      "skill": "Competitive Analysis",
      "uuid": "06f4bff367a7c2126fab2380c9dec23c",
      "confidence": null,
      "isKeySkill": false
    },
    {
      "skill": "Talent Management",
      "uuid": "098dffccb099681e86da846acfc18f82",
      "confidence": null,
      "isKeySkill": false
    },
    {
      "skill": "Management Skills",
      "uuid": "108c7c0f94f9856f016b9b385b7f111d",
      "confidence": null,
      "isKeySkill": false
    },
    {
      "skill": "Teamwork",
      "uuid": "16c129bc8a57941c7cdb12241f1058fe",
      "confidence": null,
      "isKeySkill": false
    },
    {
      "skill": "Ingredients",
      "uuid": "210c9e13155de6cf4edb59f1fbbaf4e8",
      "confidence": null,
      "isKeySkill": false
    },
    {
      "skill": "Food Hygiene standards",
      "uuid": "3acebd63c6ebf9148029998f82a04e00",
      "confidence": null,
      "isKeySkill": false
    },
    {
      "skill": "Process Improvement",
      "uuid": "3da5f4e32ad3a607108e8fbe739e9405",
      "confidence": null,
      "isKeySkill": false
    },
    {
      "skill": "Work Well Under Pressure",
      "uuid": "47e2827f5623d7107195408b20d5d598",
      "confidence": null,
      "isKeySkill": false
    },
    {
      "skill": "Reliability",
      "uuid": "820b8f74ad843d1574106ec4cadfc07e",
      "confidence": null,
      "isKeySkill": false
    },
    {
      "skill": "Food Safety Management",
      "uuid": "9e929ab9807f661aa9129846301c65a8",
      "confidence": null,
      "isKeySkill": false
    },
    {
      "skill": "Pressure",
      "uuid": "a78578c428179b490a0461e76ba5f319",
      "confidence": null,
      "isKeySkill": false
    },
    {
      "skill": "Analytical Problem Solving",
      "uuid": "b09bc18ab09b3ac0a27131f58479591f",
      "confidence": null,
      "isKeySkill": false
    },
    {
      "skill": "Nutrition",
      "uuid": "cf6586f786c56ead1647fd78046397cd",
      "confidence": null,
      "isKeySkill": false
    },
    {
      "skill": "Product Development",
      "uuid": "d324e27fb1cf5931e17c08a9a85f76bf",
      "confidence": null,
      "isKeySkill": false
    }
  ],
  "flexibleWorkArrangements": [],
  "otherRequirements": null,
  "ssocCode": "34342",
  "occupationId": "OCC014808",
  "ssocVersion": "2020v2",
  "workingHours": null,
  "numberOfVacancies": 2,
  "psdUrl": null,
  "categories": [
    {
      "id": 15,
      "category": "F&B"
    },
    {
      "id": 25,
      "category": "Manufacturing"
    }
  ],
  "employmentTypes": [
    {
      "id": 8,
      "employmentType": "Full Time"
    }
  ],
  "positionLevels": [
    {
      "id": 3,
      "position": "Manager"
    }
  ],
  "status": {
    "id": 103,
    "jobStatus": "Re-open"
  },
  "ssecEqa": "51",
  "ssecFos": "1322",
  "postedCompany": {
    "uen": "201108952N",
    "description": "<p>Born from a love of bread and a passion for quality, we are an international, company-owned, and franchised fast-casual bakery-café founded in 1988, specializing in both French and Asian-inspired goods. &nbsp;In addition to cakes, pastries, sandwiches, salads, and signature coffee &amp; tea, we offer a unique bakery and café experience to thousands of customers daily. Currently, we have over 4,000 locations worldwide, satisfying cravings and taste buds of all ages and backgrounds. Today, we invite you to become part of our storied history. No pressure. &nbsp;Apply to join a talented, diverse, collaborative, and highly competitive team—a collection of individuals united by a desire to have fun and with a passion for success. We work hard to bring world-class products and guest experiences to our customers. And with your help, we’ll continue with that mission!</p>",
    "name": "PARIS BAGUETTE SINGAPORE PTE. LTD.",
    "ssicCode": "56111",
    "employeeCount": 400,
    "companyUrl": "https://www.parisbaguette.com.sg/",
    "lastSyncDate": "2026-02-03T01:41:11.000Z",
    "ssicCode2020": "56111",
    "_links": {
      "self": {
        "href": "https://api.mycareersfuture.gov.sg/v2/companies/201108952N"
      },
      "jobs": {
        "href": "https://api.mycareersfuture.gov.sg/v2/companies/201108952N/jobs"
      },
      "addresses": {
        "href": "https://api.mycareersfuture.gov.sg/v2/companies/201108952N/addresses"
      },
      "schemes": {
        "href": "https://api.mycareersfuture.gov.sg/v2/companies/201108952N/schemes"
      }
    },
    "logoFileName": "fcece35fd0056b08c90c133ffa0a9f31/paris-baguette-singapore.png",
    "logoUploadPath": "https://static.mycareersfuture.gov.sg/images/company/logos/fcece35fd0056b08c90c133ffa0a9f31/paris-baguette-singapore.png",
    "responsiveEmployer": {
      "isResponsive": true
    }
  },
  "hiringCompany": null,
  "address": {
    "overseasCountry": null,
    "foreignAddress1": null,
    "foreignAddress2": null,
    "block": "16",
    "street": "TAI SENG STREET",
    "floor": null,
    "unit": null,
    "building": "",
    "postalCode": "534138",
    "isOverseas": false,
    "districts": [
      {
        "id": 19,
        "location": "D19 Serangoon Garden, Hougang, Sengkang, Punggol",
        "region": "North",
        "sectors": [
          "53",
          "54",
          "55",
          "82"
        ],
        "regionId": "North"
      }
    ],
    "lat": 1.33710127982761,
    "lng": 103.888471398242
  },
  "metadata": {
    "jobPostId": "MCF-2025-1719192",
    "deletedAt": "2026-01-26T17:15:05.000Z",
    "createdBy": "9122e8bd-6bfd-43be-a9c5-973911ad9145",
    "createdAt": "2025-11-10T14:22:12.000Z",
    "updatedAt": "2026-01-31T07:59:42.000Z",
    "emailRecipient": "9122e8bd-6bfd-43be-a9c5-973911ad9145",
    "editCount": 0,
    "repostCount": 2,
    "totalNumberOfView": 149,
    "newPostingDate": "2026-01-31",
    "originalPostingDate": "2025-11-10",
    "expiryDate": "2026-03-02",
    "totalNumberJobApplication": 1,
    "isPostedOnBehalf": false,
    "isHideSalary": false,
    "isHideCompanyAddress": false,
    "isHideHiringEmployerName": false,
    "isHideEmployerName": false,
    "jobDetailsUrl": "https://www.mycareersfuture.gov.sg/job/food-and-beverage/assistant-section-head-paris-baguette-singapore-587007e6a06683489166f7e7b2af4ff4",
    "matchedSkillsScore": null
  },
  "salary": {
    "maximum": 3800,
    "minimum": 2900,
    "type": {
      "id": 4,
      "salaryType": "Monthly"
    }
  },
  "_links": {
    "self": {
      "href": "https://api.mycareersfuture.gov.sg/v2/jobs/587007e6a06683489166f7e7b2af4ff4"
    },
    "screeningQuestions": {
      "href": "https://api.mycareersfuture.gov.sg/v2/jobs/587007e6a06683489166f7e7b2af4ff4/screening-questions"
    }
  },
  "jobTitles": []
}