{
  "uuid": "e865fdd003ba7af812a074759fa7b677",
  "sourceCode": "Employer Portal",
  "title": "Technical Services Specialist (Senior Executive, Fleet Maintenance)",
  "description": "<p><strong>Love engineering? Obsessed with optimization?</strong></p><p>Join our high-energy team where you'll turn ideas into action, keep our fleet running like clockwork, and learn the ropes of real-world engineering from day one.</p><p>This role ensures optimal performance, minimal downtime, and compliance with safety and environmental regulations. This position requires a combination of mechanical knowledge, system diagnostics, and operational coordination in a fast-paced environment.</p><p></p><p><strong>What You'll Be Doing</strong></p><ul><li><strong>Engineer smarter systems: </strong>Lead mini-projects to boost vehicle performance and workshop efficiency.</li><li><strong>Optimize everything:</strong> Spearhead discussion project with various vendor to upkeep fleet availability. Use data to make smart decisions on vehicle maintenance, upgrades, and replacements.</li><li><strong>Team up with pros: </strong>Work alongside technicians, contractors, and vendors to solve real problems.</li><li><strong>Innovate and improve:</strong> Suggest upgrades and tweaks to make our operations leaner and meaner.</li><li><strong>Track and report:</strong> Monitor fleet performance and share insights that drive change.</li><li><strong>Manage assets: </strong>From acquisition to retirement, help us make the most of our vehicles and equipment.</li></ul><p><strong>Who We're Looking For</strong></p><ul><li>Candidates with a Diploma/ Degree in Mechanical Engineering or Mechatronics and 3 years of relevant fleet maintenance working experience. </li><li>Curious minds who love tech, data, and solving problems.</li><li>Confident with Microsoft Office (especially Excel).</li><li>Bonus points if you know your way around heavy vehicles or have a Class 4 license (not required!).</li></ul>",
  "minimumYearsExperience": 3,
  "shiftPattern": null,
  "schemes": [],
  "skills": [
    {
      "skill": "Troubleshooting",
      "uuid": "231cf4c70d866b616c21baddaeed0696",
      "confidence": null,
      "isKeySkill": false
    },
    {
      "skill": "Microsoft Office",
      "uuid": "2482944e6048d8f3b76417f0f5af9074",
      "confidence": null,
      "isKeySkill": false
    },
    {
      "skill": "Microsoft Excel",
      "uuid": "28392dee72b88a917a72357aea20a3a5",
      "confidence": null,
      "isKeySkill": false
    },
    {
      "skill": ".NET",
      "uuid": "303cb0ef9edb9082d61bbbe5825d972a",
      "confidence": null,
      "isKeySkill": false
    },
    {
      "skill": "Hardware",
      "uuid": "3c02a379965ab0dfcd77b1c484450433",
      "confidence": null,
      "isKeySkill": false
    },
    {
      "skill": "Customer Support",
      "uuid": "45db51f999b9e9fc7263a7e0ebc2d7f0",
      "confidence": null,
      "isKeySkill": false
    },
    {
      "skill": "Critical Thinking",
      "uuid": "4fb174b9bf8f956e0c1efc8473169c24",
      "confidence": null,
      "isKeySkill": false
    },
    {
      "skill": "Class 4 License",
      "uuid": "550ad6326e7ba8a926fe6ddb2d92fb13",
      "confidence": null,
      "isKeySkill": false
    },
    {
      "skill": "Vehicles",
      "uuid": "83467144e8aa33bf67ff729d1540fa81",
      "confidence": null,
      "isKeySkill": false
    },
    {
      "skill": "Compliance",
      "uuid": "9c0408c775a2b61052a2e700a89f396f",
      "confidence": null,
      "isKeySkill": false
    },
    {
      "skill": "Networking",
      "uuid": "a5fa5746370b608090b994a97b49e98b",
      "confidence": null,
      "isKeySkill": false
    },
    {
      "skill": "Excel",
      "uuid": "c1d81af5835844b4e9d936910ded8fdc",
      "confidence": null,
      "isKeySkill": false
    },
    {
      "skill": "Vehicle Maintenance",
      "uuid": "d3a907234e76f86ba22b9551df82fd49",
      "confidence": null,
      "isKeySkill": false
    },
    {
      "skill": "Retirement",
      "uuid": "e9f3e01335524bb27f0938d3b7d7a452",
      "confidence": null,
      "isKeySkill": false
    },
    {
      "skill": "Mechanical Engineering",
      "uuid": "f47ac95069e00f0aa5cf8ed498af3bde",
      "confidence": null,
      "isKeySkill": false
    },
    {
      "skill": "Technical Support",
      "uuid": "fec5f90e9985e1f7b8cc6752739ce9b1",
      "confidence": null,
      "isKeySkill": false
    }
  ],
  "flexibleWorkArrangements": [],
  "otherRequirements": null,
  "ssocCode": "21441",
  "occupationId": "OCC002872",
  "ssocVersion": "2020v2",
  "workingHours": null,
  "numberOfVacancies": 1,
  "psdUrl": null,
  "categories": [
    {
      "id": 11,
      "category": "Engineering"
    },
    {
      "id": 33,
      "category": "Repair and Maintenance"
    },
    {
      "id": 41,
      "category": "Others"
    }
  ],
  "employmentTypes": [
    {
      "id": 7,
      "employmentType": "Permanent"
    },
    {
      "id": 8,
      "employmentType": "Full Time"
    }
  ],
  "positionLevels": [
    {
      "id": 8,
      "position": "Senior Executive"
    }
  ],
  "status": {
    "id": 102,
    "jobStatus": "Open"
  },
  "ssecEqa": "51",
  "ssecFos": "1151",
  "postedCompany": {
    "uen": "199507280G",
    "description": "<p>Cora Environment is a purpose-driven sustainable waste management company that rethinks waste. Envisioning a zero-waste future, our holistic approach empowers businesses to reduce their environmental footprint, through end-to-end solutions from waste profiling and infrastructure to resource recovery and energy-from-waste. We create value by driving industry partnerships to transform the waste landscape and shape the future for generations to come. Inspired by the words ‘collaboration’ and ‘heart’, the name “Cora” reflects our commitment to putting people, purpose and planet at the heart of everything we do.</p><p>With over 45 years of experience, Cora Environment is a leading waste management company serving the City-Punggol and Clementi-Bukit Merah sectors. We manage public, industrial, and commercial waste, and operate a material recovery facility and an energy-from-waste plant.</p>",
    "name": "CORA ENVIRONMENT PTE. LTD.",
    "ssicCode": "38100",
    "employeeCount": 750,
    "companyUrl": "https://coraenv.co/",
    "lastSyncDate": "2026-02-04T10:07:38.000Z",
    "ssicCode2020": "38100",
    "_links": {
      "self": {
        "href": "https://api.mycareersfuture.gov.sg/v2/companies/199507280G"
      },
      "jobs": {
        "href": "https://api.mycareersfuture.gov.sg/v2/companies/199507280G/jobs"
      },
      "addresses": {
        "href": "https://api.mycareersfuture.gov.sg/v2/companies/199507280G/addresses"
      },
      "schemes": {
        "href": "https://api.mycareersfuture.gov.sg/v2/companies/199507280G/schemes"
      }
    },
    "logoFileName": "50f132e5bcf85dc28b250f354e278d97/cora-environment.png",
    "logoUploadPath": "https://static.mycareersfuture.gov.sg/images/company/logos/50f132e5bcf85dc28b250f354e278d97/cora-environment.png",
    "responsiveEmployer": {
      "isResponsive": true
    }
  },
  "hiringCompany": null,
  "address": {
    "overseasCountry": null,
    "foreignAddress1": null,
    "foreignAddress2": null,
    "block": "4543",
    "street": "JALAN BUKIT MERAH",
    "floor": null,
    "unit": null,
    "building": null,
    "postalCode": "159470",
    "isOverseas": false,
    "districts": [
      {
        "id": 3,
        "location": "D03 Queenstown, Tiong Bahru",
        "region": "South",
        "sectors": [
          "14",
          "15",
          "16"
        ],
        "regionId": "South"
      }
    ],
    "lat": 1.28569747712307,
    "lng": 103.806941977699
  },
  "metadata": {
    "jobPostId": "MCF-2026-0187775",
    "deletedAt": null,
    "createdBy": "c0ed9653-7f5e-4111-bb3a-31701d6565f4",
    "createdAt": "2026-01-30T04:50:25.000Z",
    "updatedAt": "2026-01-30T04:50:25.000Z",
    "emailRecipient": "c0ed9653-7f5e-4111-bb3a-31701d6565f4",
    "editCount": 0,
    "repostCount": 0,
    "totalNumberOfView": 41,
    "newPostingDate": "2026-01-30",
    "originalPostingDate": "2026-01-30",
    "expiryDate": "2026-03-01",
    "totalNumberJobApplication": 2,
    "isPostedOnBehalf": false,
    "isHideSalary": false,
    "isHideCompanyAddress": false,
    "isHideHiringEmployerName": false,
    "isHideEmployerName": false,
    "jobDetailsUrl": "https://www.mycareersfuture.gov.sg/job/engineering/technical-services-specialist-cora-environment-e865fdd003ba7af812a074759fa7b677",
    "matchedSkillsScore": null
  },
  "salary": {
    "maximum": 4500,
    "minimum": 3000,
    "type": {
      "id": 4,
      "salaryType": "Monthly"
    }
  },
  "_links": {
    "self": {
      "href": "https://api.mycareersfuture.gov.sg/v2/jobs/e865fdd003ba7af812a074759fa7b677"
    },
    "screeningQuestions": {
      "href": "https://api.mycareersfuture.gov.sg/v2/jobs/e865fdd003ba7af812a074759fa7b677/screening-questions"
    }
  },
  "jobTitles": []
}